tensorflow_riemopt/__init__.py
tensorflow_riemopt/variable.py
tensorflow_riemopt/variable_test.py
tensorflow_riemopt/layers/__init__.py
tensorflow_riemopt/layers/embeddings.py
tensorflow_riemopt/layers/embeddings_test.py
tensorflow_riemopt/manifolds/__init__.py
tensorflow_riemopt/manifolds/approximate_mixin.py
tensorflow_riemopt/manifolds/approximate_mixin_test.py
tensorflow_riemopt/manifolds/cholesky.py
tensorflow_riemopt/manifolds/cholesky_test.py
tensorflow_riemopt/manifolds/euclidean.py
tensorflow_riemopt/manifolds/euclidean_test.py
tensorflow_riemopt/manifolds/grassmannian.py
tensorflow_riemopt/manifolds/grassmannian_test.py
tensorflow_riemopt/manifolds/hyperboloid.py
tensorflow_riemopt/manifolds/hyperboloid_test.py
tensorflow_riemopt/manifolds/mainfold_test.py
tensorflow_riemopt/manifolds/manifold.py
tensorflow_riemopt/manifolds/poincare.py
tensorflow_riemopt/manifolds/poincare_test.py
tensorflow_riemopt/manifolds/product.py
tensorflow_riemopt/manifolds/product_test.py
tensorflow_riemopt/manifolds/special_orthogonal.py
tensorflow_riemopt/manifolds/special_orthogonal_test.py
tensorflow_riemopt/manifolds/sphere.py
tensorflow_riemopt/manifolds/sphere_test.py
tensorflow_riemopt/manifolds/stiefel.py
tensorflow_riemopt/manifolds/stiefel_test.py
tensorflow_riemopt/manifolds/symmetric_positive.py
tensorflow_riemopt/manifolds/symmetric_positive_test.py
tensorflow_riemopt/manifolds/test_approximate_errors.py
tensorflow_riemopt/manifolds/test_invariants.py
tensorflow_riemopt/manifolds/test_manifold_extra.py
tensorflow_riemopt/manifolds/test_poincare_extra.py
tensorflow_riemopt/manifolds/test_product_extra.py
tensorflow_riemopt/manifolds/utils.py
tensorflow_riemopt/optimizers/__init__.py
tensorflow_riemopt/optimizers/constrained_rmsprop.py
tensorflow_riemopt/optimizers/constrained_rmsprop_test.py
tensorflow_riemopt/optimizers/riemannian_adam.py
tensorflow_riemopt/optimizers/riemannian_adam_test.py
tensorflow_riemopt/optimizers/riemannian_gradient_descent.py
tensorflow_riemopt-0.3.0.dist-info/licenses/LICENSE
tensorflow_riemopt-0.3.0.dist-info/METADATA
tensorflow_riemopt-0.3.0.dist-info/WHEEL
tensorflow_riemopt-0.3.0.dist-info/top_level.txt
tensorflow_riemopt-0.3.0.dist-info/zip-safe
tensorflow_riemopt-0.3.0.dist-info/RECORD
