Metadata-Version: 2.4
Name: tensorflow-riemopt
Version: 0.3.0
Summary: a library for optimization on Riemannian manifolds
Home-page: https://github.com/master/tensorflow-riemopt
Author: Oleg Smirnov
Author-email: oleg.smirnov@gmail.com
Keywords: tensorflow optimization machine learning
Classifier: Development Status :: 4 - Beta
Classifier: Intended Audience :: Science/Research
Classifier: License :: OSI Approved :: MIT License
Classifier: Programming Language :: Python :: 3
Classifier: Programming Language :: Python :: 3.10
Classifier: Programming Language :: Python :: 3.11
Classifier: Programming Language :: Python :: 3.12
Classifier: Topic :: Scientific/Engineering :: Mathematics
Classifier: Topic :: Software Development :: Libraries :: Python Modules
Classifier: Topic :: Software Development :: Libraries
Classifier: Operating System :: OS Independent
Requires-Python: >=3.10.0
License-File: LICENSE
Requires-Dist: tensorflow
Dynamic: author
Dynamic: author-email
Dynamic: classifier
Dynamic: description
Dynamic: description-content-type
Dynamic: home-page
Dynamic: keywords
Dynamic: license-file
Dynamic: requires-dist
Dynamic: requires-python
Dynamic: summary
